naive/__init__.py
naive/math.py
pynaive-0.2.0.dist-info/LICENSE
pynaive-0.2.0.dist-info/METADATA
pynaive-0.2.0.dist-info/WHEEL
pynaive-0.2.0.dist-info/top_level.txt
pynaive-0.2.0.dist-info/RECORD
