Metadata-Version: 2.1
Name: pynaive
Version: 0.2.0
Summary: A toy project to demonstrate Python development environment and toolchain
Home-page: https://github.com/ktrushin/pynaive
Author: Konstantin Trushin
Author-email: konstantin.trushin@gmail.com
License: MIT
Platform: UNKNOWN
Classifier: License :: OSI Approved :: MIT License
Classifier: Programming Language :: Python
Classifier: Programming Language :: Python :: 3
